{
  "en": {
    "edit.tool_select": "Select",
    "edit.tool_text": "Add text",
    "edit.tool_rect": "Rectangle",
    "edit.tool_circle": "Circle",
    "edit.tool_highlight": "Highlight",
    "edit.tool_line": "Line",
    "edit.tool_arrow": "Arrow",
    "edit.tool_freehand": "Freehand",
    "edit.tool_image": "Image",
    "edit.tool_signature": "Signature",
    "edit.tool_fallback": "Tool",
    "edit.toolbar_select": "Select",
    "edit.toolbar_text": "Text",
    "edit.toolbar_rect": "Rectangle",
    "edit.toolbar_circle": "Circle",
    "edit.toolbar_line": "Line",
    "edit.toolbar_arrow": "Arrow",
    "edit.toolbar_freehand": "Freehand",
    "edit.toolbar_highlight": "Highlight",
    "edit.toolbar_image": "Image",
    "edit.toolbar_signature": "Signature",
    "edit.undo_title": "Undo (Ctrl+Z)",
    "edit.undo_btn": "↩ Undo",
    "edit.redo_title": "Redo (Ctrl+Y)",
    "edit.redo_btn": "↪ Redo",
    "edit.label_content": "Content",
    "edit.label_font": "Font",
    "edit.label_size": "Size",
    "edit.label_color": "Color",
    "edit.label_fill": "Fill color",
    "edit.label_highlight_color": "Highlight color",
    "edit.label_opacity": "Opacity: {n}%",
    "edit.label_opacity_abbr": "Opac.: {n}%",
    "edit.label_line_width": "Width: {n}px",
    "edit.label_coord_x": "X",
    "edit.label_coord_y": "Y",
    "edit.label_width": "Width",
    "edit.label_height": "Height",
    "edit.placeholder_text": "Type text",
    "edit.hint_click_drag": "Click and drag on the page",
    "edit.hint_freehand": "Draw on the page with mouse",
    "edit.hint_select": "Click an element on the page to select it.",
    "edit.hint_text_edit": "Hover over existing text on the page. Click Edit to change content, font and color.",
    "edit.elem_text": "Text",
    "edit.elem_rect": "Rectangle",
    "edit.elem_circle": "Circle",
    "edit.elem_highlight": "Highlight",
    "edit.elem_image": "Image",
    "edit.elem_freehand": "Freehand drawing",
    "edit.elem_line": "Line",
    "edit.elem_arrow": "Arrow",
    "edit.btn_delete": "Delete",
    "edit.btn_apply": "Apply",
    "edit.btn_edit": "Edit",
    "edit.btn_cancel": "Cancel",
    "edit.btn_save": "Save",
    "edit.btn_clear": "Clear changes",
    "edit.btn_download": "Download edited PDF",
    "edit.btn_saving": "Saving...",
    "edit.btn_other_file": "Choose another file",
    "edit.success_text": "PDF with text edits downloaded!",
    "edit.success_elements": "PDF with elements downloaded!",
    "edit.msg_no_elements": "No elements to save.",
    "edit.section_text_edit": "Text editing in PDF",
    "edit.popup_heading": "Edit text",
    "edit.page_alt": "Page {n}",
    "edit.page_indicator": "Page {current} / {total}",
    "edit.element_count": "{n} elem. · {e} edits",
    "edit.text_edit_item": "P.{page}: \"{text}\"",
    "edit.default_text": "Text",
    "edit.filename_prefix": "edited-"
  },
  "pl": {
    "edit.tool_select": "Zaznaczanie",
    "edit.tool_text": "Dodawanie tekstu",
    "edit.tool_rect": "Prostokąt",
    "edit.tool_circle": "Koło",
    "edit.tool_highlight": "Zakreślacz",
    "edit.tool_line": "Linia",
    "edit.tool_arrow": "Strzałka",
    "edit.tool_freehand": "Rysunek odręczny",
    "edit.tool_image": "Obraz",
    "edit.tool_signature": "Podpis",
    "edit.tool_fallback": "Narzędzie",
    "edit.toolbar_select": "Zaznacz",
    "edit.toolbar_text": "Tekst",
    "edit.toolbar_rect": "Prostokąt",
    "edit.toolbar_circle": "Koło",
    "edit.toolbar_line": "Linia",
    "edit.toolbar_arrow": "Strzałka",
    "edit.toolbar_freehand": "Rysunek",
    "edit.toolbar_highlight": "Zakreślacz",
    "edit.toolbar_image": "Obraz",
    "edit.toolbar_signature": "Podpis",
    "edit.undo_title": "Cofnij (Ctrl+Z)",
    "edit.undo_btn": "↩ Cofnij",
    "edit.redo_title": "Ponów (Ctrl+Y)",
    "edit.redo_btn": "↪ Ponów",
    "edit.label_content": "Treść",
    "edit.label_font": "Czcionka",
    "edit.label_size": "Rozmiar",
    "edit.label_color": "Kolor",
    "edit.label_fill": "Kolor wypełnienia",
    "edit.label_highlight_color": "Kolor zakreślenia",
    "edit.label_opacity": "Przezroczystość: {n}%",
    "edit.label_opacity_abbr": "Przez.: {n}%",
    "edit.label_line_width": "Grubość: {n}px",
    "edit.label_coord_x": "X",
    "edit.label_coord_y": "Y",
    "edit.label_width": "Szer.",
    "edit.label_height": "Wys.",
    "edit.placeholder_text": "Wpisz tekst",
    "edit.hint_click_drag": "Kliknij i przeciągnij na stronie",
    "edit.hint_freehand": "Rysuj na stronie myszką",
    "edit.hint_select": "Kliknij element na stronie aby go zaznaczyć.",
    "edit.hint_text_edit": "Najedź na istniejący tekst na stronie. Kliknij Edytuj aby zmienić treść, czcionkę i kolor.",
    "edit.elem_text": "Tekst",
    "edit.elem_rect": "Prostokąt",
    "edit.elem_circle": "Koło",
    "edit.elem_highlight": "Zakreślenie",
    "edit.elem_image": "Obraz",
    "edit.elem_freehand": "Rysunek",
    "edit.elem_line": "Linia",
    "edit.elem_arrow": "Strzałka",
    "edit.btn_delete": "Usuń",
    "edit.btn_apply": "Zastosuj",
    "edit.btn_edit": "Edytuj",
    "edit.btn_cancel": "Anuluj",
    "edit.btn_save": "Zapisz",
    "edit.btn_clear": "Wyczyść zmiany",
    "edit.btn_download": "Pobierz edytowany PDF",
    "edit.btn_saving": "Zapisywanie...",
    "edit.btn_other_file": "Wybierz inny plik",
    "edit.success_text": "PDF z edycjami tekstu pobrany!",
    "edit.success_elements": "PDF z elementami pobrany!",
    "edit.msg_no_elements": "Brak elementów do zapisania.",
    "edit.section_text_edit": "Edycja tekstu w PDF",
    "edit.popup_heading": "Edytuj tekst",
    "edit.page_alt": "Strona {n}",
    "edit.page_indicator": "Strona {current} / {total}",
    "edit.element_count": "{n} elem. · {e} edycji",
    "edit.text_edit_item": "Str.{page}: \"{text}\"",
    "edit.default_text": "Tekst",
    "edit.filename_prefix": "edytowany-"
  }
}